daeclipse_cli/cli.py
daeclipse_cli/commands/__init__.py
daeclipse_cli/commands/add_art_to_groups.py
daeclipse_cli/commands/hot_tags.py
daeclipse_cli/commands/post_status.py
daeclipse_cli/commands/show_tags.py
daeclipse_cli/commands/spammer.py
daeclipse_cli/commands/user_comments.py
daeclipse_cli-0.0.1.dist-info/entry_points.txt
daeclipse_cli-0.0.1.dist-info/LICENSE
daeclipse_cli-0.0.1.dist-info/WHEEL
daeclipse_cli-0.0.1.dist-info/METADATA
daeclipse_cli-0.0.1.dist-info/RECORD
