Metadata-Version: 2.1
Name: daeclipse-cli
Version: 0.0.1
Summary: Reverse-engineered Python CLI for DeviantArt Eclipse functionality
Home-page: https://kathryndipippo.com/daeclipse-cli/
License: MIT
Keywords: python,deviantart,cli
Author: Kathryn DiPippo
Author-email: dipippo.k@gmail.com
Requires-Python: >=3.7,<4.0.0
Classifier: License :: OSI Approved :: MIT License
Classifier: Programming Language :: Python :: 3
Classifier: Programming Language :: Python :: 3.7
Classifier: Programming Language :: Python :: 3.8
Classifier: Programming Language :: Python :: 3.9
Requires-Dist: cli-ui (>=0.14.1,<0.16.0)
Requires-Dist: daeclipse (>=0.1.0,<0.2.0)
Requires-Dist: deviantart (>=0.1.5,<0.2.0)
Requires-Dist: pick (>=1.0.0,<2.0.0)
Requires-Dist: progress (>=1.6,<2.0)
Requires-Dist: python-dotenv (>=0.19.0,<0.20.0)
Requires-Dist: tabulate (>=0.8.9,<0.9.0)
Requires-Dist: typer[all] (>=0.3.2,<0.4.0)
Project-URL: Issues, https://github.com/Pepper-Wood/daeclipse-cli/issues
Project-URL: Repository, https://github.com/Pepper-Wood/daeclipse-cli
